freighter/__init__.py
freighter/encoder.py
freighter/endpoint.py
freighter/error_registry.py
freighter/errors.py
freighter/http.py
freighter/stream.py
freighter/sync.py
freighter/transport.py
freighter/unary.py
freighter/util/__init__.py
freighter/util/threading.py
freighter/ws.py
arya_freighter-0.1.0.dist-info/WHEEL
arya_freighter-0.1.0.dist-info/METADATA
arya_freighter-0.1.0.dist-info/RECORD
