Metadata-Version: 2.1
Name: arya-freighter
Version: 0.1.0
Summary: 
Author: emiliano bonilla
Author-email: emilbon99@gmail.com
Requires-Python: >=3.10,<4.0
Classifier: Programming Language :: Python :: 3
Classifier: Programming Language :: Python :: 3.10
Requires-Dist: janus (>=1.0.0,<2.0.0)
Requires-Dist: msgpack (>=1.0.4,<2.0.0)
Requires-Dist: mypy (>=0.971,<0.972)
Requires-Dist: pytest (>=7.1.2,<8.0.0)
Requires-Dist: pytest-asyncio (>=0.19.0,<0.20.0)
Requires-Dist: urllib3 (>=1.26.12,<2.0.0)
Requires-Dist: websockets (>=10.3,<11.0)
